tabCompletion/__init__.py
tabCompletion/tabCompletion.py
tabCompletion-1.0.0.dist-info/LICENSE
tabCompletion-1.0.0.dist-info/METADATA
tabCompletion-1.0.0.dist-info/WHEEL
tabCompletion-1.0.0.dist-info/top_level.txt
tabCompletion-1.0.0.dist-info/RECORD
