Metadata-Version: 2.1
Name: tabCompletion
Version: 1.0.0
Summary: This package will help impart autocompletion to your python script inputs.
Home-page: https://gitlab.com/vaisakh032/tab-auto-completion
Author: Vaisakh Anand
Author-email: vaisakh032@gmail.com
License: UNKNOWN
Platform: UNKNOWN
Classifier: Programming Language :: Python :: 3
Classifier: License :: OSI Approved :: GNU General Public License v3 or later (GPLv3+)
Classifier: Operating System :: POSIX :: Linux
Classifier: Topic :: Software Development :: Libraries :: Python Modules
Requires-Dist: pynput (>=1.4)
Requires-Dist: getch (>=1.0)
